hyperjson-0.2.4.dist-info/METADATA
hyperjson-0.2.4.dist-info/WHEEL
hyperjson.cpython-36m-x86_64-linux-gnu.so
hyperjson-0.2.4.dist-info/RECORD
