Metadata-Version: 2.1
Name: hyperjson
Version: 0.2.4
Classifier: Development Status :: 4 - Beta
Classifier: Intended Audience :: Developers
Classifier: License :: OSI Approved :: Apache Software License
Classifier: License :: OSI Approved
Classifier: Operating System :: MacOS
Classifier: Operating System :: Microsoft :: Windows
Classifier: Operating System :: POSIX :: Linux
Classifier: Programming Language :: Python :: 3
Classifier: Programming Language :: Python :: 3.5
Classifier: Programming Language :: Python :: 3.6
Classifier: Programming Language :: Python :: 3.7
Classifier: Programming Language :: Python :: 3.8
Classifier: Programming Language :: Python
Classifier: Programming Language :: Rust
Summary: A hyper-fast Python module for reading/writing JSON data
Keywords: fast json python
Home-Page: https://github.com/mre/hyperjson
Author: Matthias Endler <matthias-endler@gmx.net>
Author-Email: Matthias Endler <matthias-endler@gmx.net>
License: Apache-2.0
